pdutilities/__init__.py
pdutilities-1.0.1.dist-info/METADATA
pdutilities-1.0.1.dist-info/WHEEL
pdutilities-1.0.1.dist-info/top_level.txt
pdutilities-1.0.1.dist-info/RECORD
