Metadata-Version: 2.1
Name: pdutilities
Version: 1.0.1
Summary: Coming soon
Author-email: techds <chet_singh@berkeley.edu>
Requires-Dist: inflect
Requires-Dist: numpy
Requires-Dist: pandas
Requires-Dist: scikit-learn
Requires-Dist: seaborn
Requires-Dist: statsmodels
